proxygen_cli/__init__.py
proxygen_cli/cli/command_credentials.py
proxygen_cli/cli/command_docker.py
proxygen_cli/cli/command_instance.py
proxygen_cli/cli/command_main.py
proxygen_cli/cli/command_pytest_nhsd_apim_token.py
proxygen_cli/cli/command_secret.py
proxygen_cli/cli/command_settings.py
proxygen_cli/cli/command_spec.py
proxygen_cli/lib/auth.py
proxygen_cli/lib/constants.py
proxygen_cli/lib/credentials.py
proxygen_cli/lib/dot_proxygen.py
proxygen_cli/lib/output.py
proxygen_cli/lib/proxygen_api.py
proxygen_cli/lib/settings.py
proxygen_cli/lib/spec.py
proxygen_cli/lib/spec_server.py
proxygen_cli/lib/version.py
proxygen_cli/test/__init__.py
proxygen_cli/test/command_credentials_test.py
proxygen_cli/test/command_instance_test.py
proxygen_cli/test/command_main_test.py
proxygen_cli/test/command_pytest_nhsd_apim_token_test.py
proxygen_cli/test/command_secret_test.py
proxygen_cli/test/command_settings_test.py
proxygen_cli/test/command_spec_test.py
proxygen_cli/test/conftest.py
proxygen_cli/test/fixtures/client.key
proxygen_cli/test/fixtures/client.pem
proxygen_cli/test/fixtures/secret.txt
proxygen_cli/test/mock_private_key.py
proxygen_cli/test/validate_cli_version_test.py
proxygen_cli-3.0.0.dist-info/METADATA
proxygen_cli-3.0.0.dist-info/WHEEL
proxygen_cli-3.0.0.dist-info/entry_points.txt
proxygen_cli-3.0.0.dist-info/RECORD
