Metadata-Version: 2.4
Name: proxygen-cli
Version: 3.0.0
Summary: CLI for interacting with NHSD APIM's proxygen service
Author: Ben Strutt
Author-email: ben.strutt1@nhs.net
Requires-Python: >=3.13,<4.0
Classifier: Programming Language :: Python :: 3
Classifier: Programming Language :: Python :: 3.13
Classifier: Programming Language :: Python :: 3.14
Requires-Dist: cffi (>=1.17.1,<2.0.0)
Requires-Dist: click (>=8.1.2,<9.0.0)
Requires-Dist: cryptography (==44.0.1)
Requires-Dist: lxml (>=6.0.1,<7.0.0)
Requires-Dist: packaging (>=24.2,<25.0)
Requires-Dist: pydantic (>=1.9.1,<2.0.0)
Requires-Dist: pyjwt (>=2.9.0,<3.0.0)
Requires-Dist: pyyaml (>=6.0.3,<7.0.0)
Requires-Dist: requests (>=2.32.3,<3.0.0)
Requires-Dist: tabulate (>=0.9.0,<0.10.0)
Requires-Dist: yaspin (>=3.2.0,<4.0.0)
Project-URL: Repository, https://github.com/NHSDigital/proxygen-cli
